{"title":"﻿DPS095 AT The Lord’s Prayer  ","author":"གཙོ་བོའི་སྨོན་ལམ།","key":"Em","lyrics":{"verses":[{"verse":[{"line":[{"phrase":["Em","ནམ་མཁར་"]},{"phrase":["Am","བཞུགས་པའི་"]},{"phrase":["Bm","ངེད་ཀྱི་ཡབ།"]}]},{"line":[{"phrase":["Em","ཁྱེད་མཚན་དམ་པར་"]},{"phrase":["G","སྲུང་བར་"]},{"phrase":["D","ཤོག"]}]},{"line":[{"phrase":["G","ཁྱེད་ཀྱི་"]},{"phrase":["Em","རྒྱལ་སྲིད་"]},{"phrase":["Am","འོང་བར་"]},{"phrase":["Bm","ཤོག"]}]},{"line":[{"phrase":["Em","ཁྱེད་ཀྱི་རྒྱལ་སྲིད་"]},{"phrase":["Am7","འོང་བར་"]},{"phrase":["Em","ཤོག"]}]}]},{"verse":[{"line":[{"phrase":["","ཁྱེད་ཀྱི་དགོངས་པ་ནམ་མཁའ་བཞིན།"]}]},{"line":[{"phrase":["","ས་ལའང་དེ་ལྟར་འགྲུབ་པར་ཤོག"]}]},{"line":[{"phrase":["","ངེད་ཀྱི་ཉི་མ་རེ་རེའི་ཟས།"]}]},{"line":[{"phrase":["","དེ་རིང་ཡང་ནི་གནང་བར་མཛོད།"]}]}]},{"verse":[{"line":[{"phrase":["","ངེད་ཀྱིས་གཞན་ཉེས་སེལ་བ་ལྟར།"]}]},{"line":[{"phrase":["","ངེད་ཀྱི་སྡིག་པ་སེལ་བར་མཛོད།"]}]},{"line":[{"phrase":["","ཉམས་ཚོད་མི་ལེན་སྐྱོབ་པར་མཛོད།"]}]},{"line":[{"phrase":["","ངན་པ་ལས་ང་ཐར་པར་མཛོད།"]}]}]},{"verse":[{"line":[{"phrase":["","རྒྱལ་སྲིད་དབང་དང་གཟི་བརྗིད་ནི།"]}]},{"line":[{"phrase":["","རྒྱུན་ནས་རྒྱུན་དུ་ཁྱེད་ཀྱི་ཡིན།  "]}]},{"line":[{"phrase":["","རྒྱལ་སྲིད་དབང་དང་གཟི་བརྗིད་ནི།"]}]},{"line":[{"phrase":["","རྒྱུན་ནས་རྒྱུན་དུ་ཁྱེད་ཀྱི་ཡིན།  "]}]}]},{"verse":[{"line":[{"phrase":[""," "]}]}]},{"verse":[]}]}}